urltools/__init__.py
urltools/urltools.py
urltools/tests/__init__.py
urltools/tests/test_urltools.py
urltools/tests/tymer_urltools.py
urltools2-0.3.2.dist-info/LICENSE
urltools2-0.3.2.dist-info/METADATA
urltools2-0.3.2.dist-info/WHEEL
urltools2-0.3.2.dist-info/top_level.txt
urltools2-0.3.2.dist-info/RECORD
